Metadata-Version: 2.1
Name: mminepy
Version: 1.7.2
Summary: minepy from elbert06
Home-page: UNKNOWN
Author: elbert06
Author-email: elbert06@hanmail.net
License: MIT
Platform: UNKNOWN
Requires-Python: >=3
